django_pony_forms/__init__.py
django_pony_forms/models.py
django_pony_forms/pony_forms.py
django_pony_forms/templates/django_pony_forms/base_form.html
django_pony_forms/templates/django_pony_forms/errorlist.html
django_pony_forms/templates/django_pony_forms/label.html
django_pony_forms/templates/django_pony_forms/row.html
django_pony_forms-1.1.0.dist-info/LICENSE.rst
django_pony_forms-1.1.0.dist-info/METADATA
django_pony_forms-1.1.0.dist-info/WHEEL
django_pony_forms-1.1.0.dist-info/top_level.txt
django_pony_forms-1.1.0.dist-info/RECORD
